neuro_deblur/__init__.py
neuro_deblur/download.py
neuro_deblur/inference.py
neuro_deblur/model.py
neuro_deblur/utils.py
neuro_deblur-0.1.1.dist-info/licenses/LICENSE
neuro_deblur-0.1.1.dist-info/METADATA
neuro_deblur-0.1.1.dist-info/WHEEL
neuro_deblur-0.1.1.dist-info/top_level.txt
neuro_deblur-0.1.1.dist-info/RECORD
