Metadata-Version: 2.4
Name: neuro-deblur
Version: 0.1.1
Summary: Professional image and video deblurring using NAFNet
Home-page: https://github.com/Parshva2605/neuro-deblur
Author: Parshva Shah
Author-email: Parshva Shah <shahparshva2005@gmail.com>
License: MIT
Project-URL: Homepage, https://github.com/Parshva2605/neuro-deblur
Project-URL: Documentation, https://github.com/Parshva2605/neuro-deblur#readme
Project-URL: Repository, https://github.com/Parshva2605/neuro-deblur
Project-URL: Bug Tracker, https://github.com/Parshva2605/neuro-deblur/issues
Keywords: deblur,image-processing,video-processing,nafnet,deep-learning
Classifier: Development Status :: 4 - Beta
Classifier: Intended Audience :: Developers
Classifier: Intended Audience :: Science/Research
Classifier: Topic :: Scientific/Engineering :: Artificial Intelligence
Classifier: Topic :: Scientific/Engineering :: Image Processing
Classifier: License :: OSI Approved :: MIT License
Classifier: Programming Language :: Python :: 3
Classifier: Programming Language :: Python :: 3.9
Classifier: Programming Language :: Python :: 3.10
Classifier: Programming Language :: Python :: 3.11
Classifier: Programming Language :: Python :: 3.12
Requires-Python: >=3.9
License-File: LICENSE
Requires-Dist: torch>=2.0.0
Requires-Dist: torchvision>=0.15.0
Requires-Dist: opencv-python>=4.5.0
Requires-Dist: numpy>=1.21.0
Requires-Dist: pillow>=9.0.0
Requires-Dist: tqdm>=4.60.0
Provides-Extra: dev
Requires-Dist: pytest>=7.0; extra == "dev"
Requires-Dist: black>=22.0; extra == "dev"
Requires-Dist: flake8>=4.0; extra == "dev"
Dynamic: author
Dynamic: home-page
Dynamic: license-file
Dynamic: requires-python
